pycards/__init__.py
pycards/data.json
pycards/settings.py
pycards/cards/__init__.py
pycards/cards/card.py
pycards/cards/creditcard.py
python_cards-1.3.dist-info/DESCRIPTION.rst
python_cards-1.3.dist-info/METADATA
python_cards-1.3.dist-info/RECORD
python_cards-1.3.dist-info/WHEEL
python_cards-1.3.dist-info/metadata.json
python_cards-1.3.dist-info/top_level.txt
tests/__init__.py
tests/test_amex.py
tests/test_aura.py
tests/test_card.py
tests/test_dinners.py
tests/test_discover.py
tests/test_elo.py
tests/test_jcb.py
tests/test_mastercard.py
tests/test_visa.py
tests/tets_hipercard.py
