Metadata-Version: 2.0
Name: python-cards
Version: 1.3
Summary: Set of classes for validating, identifying and formatting do credit cards and debit cards.
Home-page: https://github.com/mrlucascardoso/pycards
Author: Lucas Cardoso
Author-email: mr.lucascardoso@gmail.com
License: MIT License
Keywords: creditcard
Platform: UNKNOWN
Classifier: License :: OSI Approved :: MIT License
Classifier: Operating System :: OS Independent
Classifier: Programming Language :: Python :: 2.7
Classifier: Programming Language :: Python :: 3
Classifier: Programming Language :: Python :: 3.4
Classifier: Programming Language :: Python :: 3.5
